pyskat/__about__.py
pyskat/__init__.py
pyskat/__main__.py
pyskat/cli.py
pyskat/database.py
pyskat/settings.py
pyskat/api/__init__.py
pyskat/api/evaluation.py
pyskat/api/match.py
pyskat/api/player.py
pyskat/api/result.py
pyskat/api/session.py
pyskat/data_model/__init__.py
pyskat/data_model/deep_responses.py
pyskat/data_model/match.py
pyskat/data_model/player.py
pyskat/data_model/player_match_link.py
pyskat/data_model/result.py
pyskat/data_model/session.py
pyskat/data_model/shuffle_matches.py
pyskat/data_model/utils.py
pyskat/static/acorns_suit.svg
pyskat/static/bells_suit.svg
pyskat/static/hearts_suit.svg
pyskat/static/leafs_suit.svg
pyskat/static/pyskat_icon.svg
pyskat/static/pyskat_logo.svg
pyskat/wui/__init__.py
pyskat/wui/evaluation.py
pyskat/wui/jinja.py
pyskat/wui/matches.py
pyskat/wui/messages.py
pyskat/wui/players.py
pyskat/wui/results.py
pyskat/wui/sessions.py
pyskat/wui/templates/base.html
pyskat/wui/templates/evaluation.html
pyskat/wui/templates/index.html
pyskat/wui/templates/macros.html
pyskat/wui/templates/matches.html
pyskat/wui/templates/players.html
pyskat/wui/templates/results.html
pyskat/wui/templates/sessions.html
pyskat/wui/templates/evaluation_displays/plot_lost.html
pyskat/wui/templates/evaluation_displays/plot_opponents_lost.html
pyskat/wui/templates/evaluation_displays/plot_scores.html
pyskat/wui/templates/evaluation_displays/plot_won.html
pyskat/wui/templates/evaluation_displays/table.html
pyskat-0.3.0.post1.dist-info/METADATA
pyskat-0.3.0.post1.dist-info/WHEEL
pyskat-0.3.0.post1.dist-info/entry_points.txt
pyskat-0.3.0.post1.dist-info/licenses/LICENSE
pyskat-0.3.0.post1.dist-info/RECORD
