Metadata-Version: 2.4
Name: pyskat
Version: 0.3.0.post1
Summary: A web application for managing tournaments in the Skat card game
Project-URL: Documentation, https://codeberg.org/axtimhaus/pyskat/src/branch/main/README.md
Project-URL: Issues, https://codeberg.org/axtimhaus/pyskat/issues
Project-URL: Source, https://codeberg.org/axtimhaus/pyskat/
Author-email: Max Weiner <max.weiner@posteo.de>
License-Expression: MIT
License-File: LICENSE
Classifier: Development Status :: 3 - Alpha
Classifier: Programming Language :: Python
Classifier: Programming Language :: Python :: 3.10
Classifier: Programming Language :: Python :: 3.11
Classifier: Programming Language :: Python :: 3.12
Classifier: Programming Language :: Python :: Implementation :: CPython
Requires-Python: >=3.10
Requires-Dist: fastapi[standard]~=0.117.0
Requires-Dist: itsdangerous~=2.2
Requires-Dist: pandas~=2.2
Requires-Dist: plotly-bootstrap-templates~=2.1
Requires-Dist: plotly~=6.0
Requires-Dist: pluggy~=1.2
Requires-Dist: pydantic-settings~=2.7
Requires-Dist: rich~=13.7
Requires-Dist: sqlmodel~=0.0.22
Requires-Dist: tomli-w>=1.2.0
Requires-Dist: typer~=0.15.0
